digit_recognition.py
install_network.py
nn_functions.py
digit_recognition-0.0.11.dist-info/METADATA
digit_recognition-0.0.11.dist-info/WHEEL
digit_recognition-0.0.11.dist-info/entry_points.txt
digit_recognition-0.0.11.dist-info/top_level.txt
digit_recognition-0.0.11.dist-info/RECORD
