Metadata-Version: 2.1
Name: digit-recognition
Version: 0.0.11
Summary: Neural network for digit recognition
Home-page: https://github.com/Mittenbuhler/Neural_Network.git
Author: Maximilian Mittenbuhler
Author-email: max.mittenbuhler@student.uva.nl
License: UNKNOWN
Platform: UNKNOWN
Classifier: Programming Language :: Python :: 3
Classifier: License :: OSI Approved :: MIT License
Classifier: Operating System :: OS Independent
Requires-Dist: numpy
Requires-Dist: idx2numpy
Requires-Dist: urllib3
Requires-Dist: Pillow
